{"guide_compatibility.md":"CV1WTNCN","config_index.md":"V8HgZDpJ","hook_basic-config.md":"DCBu2XF6","hook_getting-start.md":"De7Dkd3n","guide_index.md":"DnCzhDB7","hook_index.md":"V7l_NZhl","guide_hooks.md":"DUtVBidR","hook_compatibility.md":"DOa1EnFL","changelog.md":"DDPRiDf9","go_index.md":"C0HljJ7i","guide_basic-config.md":"B-6EidWI","example_index.md":"DhKWyAQk","ui_bak_index.md":"BX29LBv3","guide_getting-start.md":"BZMQ6glz","index.md":"BXGBEXpq","hook_features.md":"6TtLiWsf","api_index.md":"CRb0ycHp"}
